LICENSE
MANIFEST.in
README.md
setup.py
django_hudson/__init__.py
django_hudson/models.py
django_hudson/tests.py
django_hudson/xmlrunner.py
django_hudson.egg-info/PKG-INFO
django_hudson.egg-info/SOURCES.txt
django_hudson.egg-info/dependency_links.txt
django_hudson.egg-info/not-zip-safe
django_hudson.egg-info/requires.txt
django_hudson.egg-info/top_level.txt
django_hudson/management/__init__.py
django_hudson/management/commands/__init__.py
django_hudson/management/commands/hudson.py
django_hudson/management/commands/lint.py
django_hudson/management/commands/pylint.rc
django_hudson/management/commands/xmltest.py
tests/__init__.py
tests/__init__.pyc
tests/manage.py
tests/requirements.pip
tests/settings.py
tests/settings.pyc