Metadata-Version: 1.0
Name: django-hudson
Version: 0.9.1
Summary: Plug and play continuous integration with django and hudson
Home-page: http://github.com/kmmbvnr/django-hudson
Author: Mikhail Podgurskiy
Author-email: kmmbvnr@gmail.com
License: LGPL
Keywords: pyunit,unittest,testrunner,hudson,django
Platform: Any
Classifier: Development Status :: 4 - Beta
Classifier: Intended Audience :: Developers
Classifier: License :: OSI Approved :: GNU Library or Lesser General Public License (LGPL)
Classifier: Natural Language :: English
Classifier: Operating System :: OS Independent
Classifier: Programming Language :: Python
Classifier: Topic :: Software Development :: Libraries :: Python Modules
Classifier: Topic :: Software Development :: Testing
